LICENSE
MANIFEST.in
README.md
requirements.txt
setup.cfg
setup.py
sgmarkets_api_analytics_data/__init__.py
sgmarkets_api_analytics_data/__meta__.py
sgmarkets_api_analytics_data/_error_msg.py
sgmarkets_api_analytics_data/_obj_from_dict.py
sgmarkets_api_analytics_data/_util.py
sgmarkets_api_analytics_data/endpoint_info.py
sgmarkets_api_analytics_data/endpoints.py
sgmarkets_api_analytics_data/info.py
sgmarkets_api_analytics_data/request_data_fields_values.py
sgmarkets_api_analytics_data/request_data_instruments.py
sgmarkets_api_analytics_data/request_data_intraday_quotes.py
sgmarkets_api_analytics_data/request_data_last_quotes.py
sgmarkets_api_analytics_data/request_data_live_quotes.py
sgmarkets_api_analytics_data/request_data_product.py
sgmarkets_api_analytics_data/request_data_product_fields.py
sgmarkets_api_analytics_data/request_data_quota.py
sgmarkets_api_analytics_data/request_data_quotes.py
sgmarkets_api_analytics_data/request_data_snapshot_quotes.py
sgmarkets_api_analytics_data/response_data_fields_values.py
sgmarkets_api_analytics_data/response_data_instruments.py
sgmarkets_api_analytics_data/response_data_intraday_quotes.py
sgmarkets_api_analytics_data/response_data_last_quotes.py
sgmarkets_api_analytics_data/response_data_live_quotes.py
sgmarkets_api_analytics_data/response_data_product.py
sgmarkets_api_analytics_data/response_data_product_fields.py
sgmarkets_api_analytics_data/response_data_quota.py
sgmarkets_api_analytics_data/response_data_quotes.py
sgmarkets_api_analytics_data/response_data_snapshot_quotes.py
sgmarkets_api_analytics_data.egg-info/PKG-INFO
sgmarkets_api_analytics_data.egg-info/SOURCES.txt
sgmarkets_api_analytics_data.egg-info/dependency_links.txt
sgmarkets_api_analytics_data.egg-info/not-zip-safe
sgmarkets_api_analytics_data.egg-info/requires.txt
sgmarkets_api_analytics_data.egg-info/top_level.txt
sgmarkets_api_analytics_data/markdown/fields_values.md
sgmarkets_api_analytics_data/markdown/info.md
sgmarkets_api_analytics_data/markdown/instruments.md
sgmarkets_api_analytics_data/markdown/intraday_quotes.md
sgmarkets_api_analytics_data/markdown/last_quotes.md
sgmarkets_api_analytics_data/markdown/live_quotes.md
sgmarkets_api_analytics_data/markdown/products.md
sgmarkets_api_analytics_data/markdown/products_fields.md
